fairtorch/__init__.py
fairtorch/constraint.py
fairtorch-0.1.2.dist-info/LICENSE
fairtorch-0.1.2.dist-info/WHEEL
fairtorch-0.1.2.dist-info/METADATA
fairtorch-0.1.2.dist-info/RECORD
