Metadata-Version: 2.1
Name: fairtorch
Version: 0.1.2
Summary: 
License: MIT
Author: Masashi Sode
Author-email: masashi.sode@gmail.com
Requires-Python: >=3.6.5,<4.0.0
Classifier: License :: OSI Approved :: MIT License
Classifier: Programming Language :: Python :: 3
Classifier: Programming Language :: Python :: 3.7
Classifier: Programming Language :: Python :: 3.8
Classifier: Programming Language :: Python :: 3.9
Requires-Dist: torch (>=1.6.0,<2.0.0)
